{"ocr_results":[{"text":"大把革命引向胜利，历史已经作了结论，党内同志没有什么不同看","box":[[65,34],[877,32],[878,55],[65,58]]},{"text":"法了。十二大将把建设引向胜利，党内绝大多数同志和广大群众相","box":[[63,83],[880,82],[880,110],[63,111]]},{"text":"信这个判断，少数同志因为对情况缺乏全面的了解，不那么相信。当","box":[[63,135],[878,134],[878,158],[63,159]]},{"text":"然也有个别同忘同中央政治上不一致，因此对十二大的估计就同绝","box":[[63,186],[878,186],[878,209],[63,209]]},{"text":"大多数同志很不一样。到底小平同志的判断有没有根据？根据是什","box":[[63,237],[880,237],[880,260],[63,260]]},{"text":"么？根据够不够？胡耀邦同志作的报告的第一部分，实际上已经回答","box":[[63,286],[880,287],[880,311],[63,310]]},{"text":"了这个问题。开幕词中有这么几句话：“和八大的时候比较，现在我们","box":[[65,336],[881,338],[881,362],[65,360]]},{"text":"党对我国社会主义建设规律的认识深刻得多了，经验丰富得多了，贯","box":[[64,387],[881,389],[881,412],[64,411]]},{"text":"彻执行我们的正确方针的自觉性和坚定性大大加强了。”讲根据，可","box":[[62,437],[880,440],[880,464],[62,461]]},{"text":"以列出很多方面的材料，但从制定党的路线这个意义上说，小平同志","box":[[63,488],[881,490],[881,513],[63,511]]},{"text":"的这几句话，是最重要的，是高度概括了上述判断的充分根据的。","box":[[61,536],[869,538],[868,565],[61,563]]},{"text":"下面，我从四个方面讲点体会。","box":[[117,589],[500,591],[500,615],[117,612]]},{"text":"（一）关于对我国社会主义建设规律的认识问题。","box":[[132,641],[727,641],[727,665],[132,665]]},{"text":"1·列宁在《唯物主义与经验批判主义》中说：“在认识论上","box":[[124,692],[882,692],[882,716],[124,716]]},{"text":"和在科学的其他一切领域中一样，我们应该辩证地思考，也就是","box":[[61,741],[882,743],[882,767],[61,765]]},{"text":"说，不要以为我们的认识是一成不变的，而要去分析怎样从不知到","box":[[61,792],[881,793],[881,817],[61,816]]},{"text":"知，怎样从不完全的不确切的知识到比较完全比较确切的知识。”","box":[[57,841],[870,837],[871,867],[57,871]]},{"text":"（《列宁选集》第2卷第100页）","box":[[72,891],[362,891],[362,914],[72,914]]},{"text":"十二大政治报告的第一部分，从思想、政治、组织、经济、文","box":[[117,941],[881,944],[881,967],[117,965]]},{"text":"化教育、军事、党的建设等方面，说明我们在三中全会以后，不但","box":[[62,994],[881,994],[881,1017],[62,1017]]},{"text":"在指导思想上，而且在实际工作中分清了是非，完成了拨乱反正的","box":[[60,1043],[879,1043],[879,1066],[60,1066]]},{"text":"任务。我们对于我国社会主义建设规律的认识，通过总结三十多年","box":[[60,1094],[881,1094],[881,1118],[60,1118]]},{"text":"来的丰富经验，已经从过去那种不完全、不准确的状况，发展到现","box":[[58,1144],[880,1145],[880,1168],[58,1167]]},{"text":"在比较完全、比较准确了。对于任何规律的认识，对于任何事物的","box":[[59,1194],[879,1195],[879,1219],[59,1218]]},{"text":"认识，都要通过一个过程。想一眼就把事物的规律看准，正确地把","box":[[58,1244],[879,1246],[879,1273],[58,1271]]},{"text":"2","box":[[73,1295],[92,1295],[92,1321],[73,1321]]}],"dimensions":{"height":1332,"width":954}}