{"ocr_results":[{"text":"村》更好的作品，因为读者需要！”","box":[[178,300],[630,298],[630,328],[178,330]]},{"text":"到这里，就是坦克车正要来，或将要来了，不妨先折断了投","box":[[241,353],[1009,353],[1009,377],[241,377]]},{"text":"枪。","box":[[179,403],[232,403],[232,430],[179,430]]},{"text":"到这里，我又应该补叙狄克先生的文章的题目，是：“我们要","box":[[240,453],[1011,455],[1011,479],[240,477]]},{"text":"执行自我批判”。","box":[[178,502],[396,504],[396,531],[178,529]]},{"text":"题目很有劲。作者虽然不说这就是“自我批判”，但却实行着","box":[[239,556],[1011,556],[1011,580],[239,580]]},{"text":"抹杀《八月的乡村》的“自我批判”的任务的，要到他所希望的正","box":[[178,603],[1010,605],[1010,632],[178,630]]},{"text":"式的“自我批判”发表时，这才解除它的任务，而《八月的乡村》","box":[[180,654],[1005,655],[1005,682],[180,681]]},{"text":"也许再有些生机。因为这种模模糊糊的摇头，比列举十大罪状更有","box":[[180,706],[1010,708],[1010,732],[180,729]]},{"text":"害于对手，列举还有条款，含糊的指摘，是可以令人揣测到坏到茫","box":[[178,756],[1008,758],[1008,782],[178,780]]},{"text":"无界限的。","box":[[178,806],[307,806],[307,833],[178,833]]},{"text":"自然，狄克先生的“要执行自我批判”是好心，因为“那些作","box":[[239,859],[1009,859],[1009,883],[239,883]]},{"text":"家是我们底”的缘故。但我以为同时可也方方忘记不得“我们”之","box":[[177,908],[1009,910],[1009,934],[177,932]]},{"text":"外的“他们”，也不可专对“我们”之中的“他们”。要批判，就","box":[[178,957],[1010,958],[1010,985],[178,984]]},{"text":"得彼此都给批判，美恶一并指出。如果在还有“我们”和“他们”","box":[[175,1007],[997,1008],[997,1034],[175,1033]]},{"text":"的文坛上，一味自责以显其·“正确”或公平，那其实是在向“他","box":[[178,1059],[1008,1060],[1008,1084],[178,1083]]},{"text":"们”献媚或替“他们”缴械。","box":[[178,1110],[535,1110],[535,1137],[178,1137]]},{"text":"四月十六日。","box":[[786,1181],[941,1181],[941,1208],[786,1208]]},{"text":"（注：这篇文章是鲁迅一九三六年写的）","box":[[453,1256],[936,1256],[936,1280],[453,1280]]},{"text":"·8·","box":[[200,1508],[257,1508],[257,1533],[200,1533]]}],"dimensions":{"height":1754,"width":1241}}