{"ocr_results":[{"text":"第","box":[[856,156],[952,156],[952,185],[856,185]]},{"text":"页","box":[[960,159],[989,159],[989,180],[960,180]]},{"text":"质的人、的准备多害材料报局按退鸦处理","box":[[210,246],[935,250],[934,300],[209,297]]},{"text":"何发少发之资都些救补发","box":[[244,339],[691,347],[691,390],[243,383]]},{"text":"装","box":[[68,645],[89,645],[89,714],[68,714]]},{"text":"北京市电車公司印刷厂出品七一","box":[[38,689],[61,689],[61,937],[38,937]]},{"text":"平血厂政仙","box":[[705,700],[925,705],[924,754],[704,749]]},{"text":"11.25","box":[[800,805],[879,805],[879,826],[800,826]]},{"text":"线品","box":[[69,946],[88,946],[88,988],[69,988]]},{"text":"(1229)","box":[[195,1483],[249,1483],[249,1504],[195,1504]]}],"dimensions":{"height":1565,"width":1117}}