{"ocr_results":[{"text":"5、徐景贤的揭发交代","box":[[462,264],[725,263],[725,287],[462,288]]},{"text":"影印件原文","box":[[714,335],[908,335],[908,359],[714,359]]},{"text":"Y","box":[[404,378],[433,376],[434,384],[405,386]]},{"text":"“四人帮”和他们在文化部的亲","box":[[676,380],[991,382],[991,406],[676,404]]},{"text":"信拖杀影片《园丁之歌》，直接反对","box":[[628,414],[990,415],[990,436],[628,434]]},{"text":"8","box":[[248,445],[282,445],[282,455],[248,455]]},{"text":"华国锋同志。一九七四年春天，国","box":[[629,446],[989,446],[989,466],[629,466]]},{"text":"092","box":[[222,466],[245,466],[245,473],[222,473]]},{"text":"2833","box":[[279,464],[314,464],[314,475],[279,475]]},{"text":"务院文化组就告诉上海准备批判，","box":[[629,477],[975,477],[975,497],[629,497]]},{"text":"送82","box":[[288,503],[338,503],[338,510],[288,510]]},{"text":"车","box":[[526,505],[563,505],[563,515],[526,515]]},{"text":"市委布置报社印剧本、写文章（当","box":[[630,508],[989,508],[989,528],[630,528]]},{"text":"9","box":[[502,524],[552,524],[552,535],[502,535]]},{"text":"时我住医院），七月十九日国务院文","box":[[628,537],[989,538],[989,561],[627,560]]},{"text":"化组发出批判《园丁之歌》的通知","box":[[630,571],[990,571],[990,591],[630,591]]},{"text":"后，我紧紧跟上，要上海报纸积极参","box":[[630,601],[988,602],[988,623],[630,622]]},{"text":"加批判，连续发了初澜等的文章，","box":[[629,633],[975,633],[975,653],[629,653]]},{"text":"并市置工农兵作者写文章。这时，","box":[[630,665],[975,665],[975,685],[630,685]]},{"text":"我也看到了传来的张春桥、姚文元","box":[[629,696],[987,696],[987,716],[629,716]]},{"text":"23","box":[[536,706],[558,706],[558,714],[536,714]]},{"text":"的黑批示，姚文元批道：“《国丁之","box":[[628,726],[987,726],[987,748],[628,748]]},{"text":"988","box":[[465,742],[490,742],[490,749],[465,749]]},{"text":"歌》宣传的路线以及歌颂的人物都","box":[[629,757],[988,757],[988,777],[629,777]]},{"text":"20","box":[[328,771],[360,771],[360,778],[328,778]]},{"text":"8","box":[[350,775],[448,775],[448,785],[350,785]]},{"text":"是错误的。”国务院文化组的通知写","box":[[629,789],[987,789],[987,809],[629,809]]},{"text":"3","box":[[492,813],[550,815],[550,823],[492,821]]},{"text":"得十分明白：《园丁之歌》是“内容有","box":[[629,820],[987,820],[987,840],[629,840]]},{"text":"严重错误的坏戏”，“否定无产阶级","box":[[627,851],[987,851],[987,871],[627,871]]},{"text":"32","box":[[347,887],[398,886],[398,894],[347,895]]},{"text":"文化大革命”、“为反革命的修正主","box":[[624,883],[987,883],[987,903],[624,903]]},{"text":"义教育路线招魂”、“向无产阶级反文倒算”，扣了三顶大赠子，而且还盗用中央","box":[[186,914],[988,913],[988,934],[186,935]]},{"text":"名义，说什么“经中央批准，决定在京、津、沪、湖南四省市·….……进行批判。”","box":[[184,944],[989,942],[989,965],[184,967]]},{"text":"这其实就是江青下达的“圣旨”。于是我不但在上海报纸上组织批判，而且在","box":[[185,977],[990,975],[990,996],[185,998]]},{"text":"七四年八月上海的一个教育革命座谈会上，学着“四人帮”的腔调，大讲什么：","box":[[186,1008],[988,1007],[988,1027],[186,1028]]},{"text":"“《园丁之歌》，中央领导（“四人帮”）指出电影所歌颂的路线和人物都是错误","box":[[186,1038],[991,1037],[991,1058],[186,1059]]},{"text":"的。所歌颂的是修正主义路线，宣扬智育第一、文化至上。对学生实行管卡","box":[[186,1070],[990,1068],[990,1089],[186,1091]]},{"text":"压或搞软的一手诱导，便他们走上修正主义道路：最后培养为资产阶级接班","box":[[187,1103],[992,1100],[992,1120],[187,1123]]},{"text":"人。”我还攻击“影片宣扬知识分子领导学校，否定无产阶级文化大革命，否定","box":[[187,1133],[991,1131],[991,1152],[187,1154]]},{"text":"无产阶级教育革命····一九七二年还出这样的影片，说明路线斗争在继续。”","box":[[186,1164],[993,1159],[993,1183],[186,1188]]},{"text":"我大肆攻击影片里的女教员之后，还压制激育战线上同志们的不同意见，我","box":[[188,1196],[992,1194],[992,1215],[188,1217]]},{"text":"胡说“在我们教师队伍皇有一部分人还有这样的反映，看到这样的教师还认","box":[[188,1229],[990,1225],[990,1245],[188,1249]]},{"text":"为是好教师，从影片看不出有害问题”等等，我这样说，完全是颠倒黑自，把","box":[[188,1260],[990,1256],[990,1276],[188,1280]]},{"text":"华国锋同志亲自关怀下拍摄的歌颂毛主席的无产阶级教育路线的影片一棍子","box":[[188,1291],[988,1287],[988,1307],[188,1312]]},{"text":"打死，搞乱人们的思想。这还不算，七四年八月，我决定上海话剧团的独票","box":[[187,1323],[989,1317],[989,1338],[187,1343]]},{"text":"话剧《小将》上北京参加全国文艺调演时，还鼓动剧团的同志“和《园丁之歌》","box":[[188,1354],[990,1348],[990,1369],[188,1375]]},{"text":"对着平”，妄图拖人下水。这是把矛头对着华国锋同志的。","box":[[188,1386],[796,1382],[797,1402],[188,1406]]},{"text":"徐景贤","box":[[626,1413],[748,1411],[749,1435],[627,1437]]},{"text":"一九七六年十二月八日","box":[[676,1445],[914,1441],[914,1462],[676,1466]]},{"text":"145","box":[[538,1501],[646,1501],[646,1526],[538,1526]]}],"dimensions":{"height":1754,"width":1241}}