{"ocr_results":[{"text":"首好诗，使人一见生情，进而为《刘三姐》的重新上演叫好，为“四人帮”扼杀此剧而无比","box":[[172,241],[1064,242],[1064,266],[172,265]]},{"text":"愤概。","box":[[171,277],[229,277],[229,298],[171,298]]},{"text":"善于突出最重要、最新鲜、最精彩的事实，目的是为了突出主题。","box":[[215,310],[852,313],[852,336],[215,333]]},{"text":"新华社一月十三日报道的《如何解决“抓药难”的间题？》一稿，好在敢抓群众关心的","box":[[215,344],[1067,345],[1067,369],[215,368]]},{"text":"追切问题。从写作的角度看，记者如果不开动脑筋，很可能写成-一篇老一套的会议新闻。报","box":[[170,379],[1067,380],[1067,401],[170,400]]},{"text":"道开头提出问题的方式是比较吸引人的，这样就把话说到了群众的心里，一开头就引起了读","box":[[171,414],[1067,414],[1067,434],[171,434]]},{"text":"者的共鸣。","box":[[170,447],[270,444],[271,465],[170,468]]},{"text":"善于突出新鲜的事实，才能写得不雷同，有特点。《〈刘三姐〉重新上演》一稿把背景","box":[[217,478],[1070,478],[1070,502],[217,502]]},{"text":"材料提到前面来写，不是也很吸引人吗？现在有些新闻好象被一种无形的框框“框”住了，","box":[[171,512],[1060,512],[1060,535],[171,535]]},{"text":"写外宾要从下飞机写起，写会议要从主席台写起，写生产要从抓革命写起，写战备要从大批","box":[[171,546],[1073,546],[1073,569],[171,569]]},{"text":"判写起。是否每一篇都要这样写呢？千部一腔，又怎能引人人胜呢？记得一位记者谈到他写","box":[[170,578],[1073,579],[1073,603],[170,602]]},{"text":"罗马尼亚一个代表团去北京市郊中罗友好人民公社访问参观，原稿完全按一般参观访问的程","box":[[171,613],[1075,613],[1075,636],[171,636]]},{"text":"序，-上来就是锣鼓鲜花等欢迎场面，接着是宾主讲话，最后写到代表团赠送了一批罗马尼","box":[[171,647],[1074,647],[1074,671],[171,671]]},{"text":"亚的小麦、大豆、蔬菜种子和葡萄种子和葡萄秧。记者第二天打开报纸一看，大吃一惊，编","box":[[170,681],[1077,679],[1077,703],[170,705]]},{"text":"者把原稿结尾部分的事实调到新闻的开头去写，强调了让罗中人民友好的种子在中国土地上","box":[[171,714],[1076,713],[1076,736],[171,737]]},{"text":"开花结果。这正是：编辑慧眼识真金，遂使新闻动人心。","box":[[170,745],[726,747],[726,774],[170,772]]},{"text":"我们经常看到一些新闻，问题是抓得好的，但表达时不善于突出精华。比如写某师政治","box":[[218,780],[1077,777],[1077,801],[218,804]]},{"text":"干部学习军事尝到甜头，这是很好的新闻题材，但写法上开头是抽象空洞的导语，接着是背","box":[[171,811],[1079,806],[1079,833],[171,838]]},{"text":"景，再就是做法，最后是效果。这叫做问题新鲜，题材新鲜，写法不新鲜。是否可以把效果","box":[[171,845],[1079,840],[1079,867],[171,872]]},{"text":"部分最典型的事实提前来写，使人一下子信服政治干部学习军事的重要意义呢？","box":[[171,880],[957,875],[958,902],[171,907]]},{"text":"二、有点悬念","box":[[526,941],[731,937],[731,958],[526,962]]},{"text":"写新闻不要摆出-副正襟危坐的架势，老是一本正经、平铺直叙。笔调要活泼，有变","box":[[218,981],[1085,977],[1085,1005],[218,1009]]},{"text":"化。有时，事情的主人或原因、结果，可以先不直说，造成一个“悬念”，使人越读越想知","box":[[168,1014],[1087,1007],[1087,1040],[168,1046]]},{"text":"道那个“谜底”，这也是引起人们兴趣的一种方法。”“","box":[[166,1042],[736,1032],[737,1076],[167,1086]]},{"text":"今年三月三十日《解放军报》刊登的消息《“这个第一我们不能要”》，开头写在一次","box":[[217,1074],[1089,1070],[1089,1106],[217,1110]]},{"text":"全师军事体育运动会上，南京部队某团的一连参加了六项比赛，获得了总分第一名。成绩已","box":[[169,1108],[1089,1102],[1089,1139],[169,1145]]},{"text":"经评定，锦旗就要颁发。就在这时，团政委姜海春给师首长打电话，请求师里取消一连的第","box":[[170,1141],[1090,1138],[1090,1172],[170,1175]]},{"text":"一-名，把名次排到最后面。这就造成了“悬念”。读者看到这里，很自然产生疑问：这到底","box":[[170,1173],[1092,1169],[1092,1205],[170,1209]]},{"text":"是怎么--回事呀？文章接着交代：一连为了以绝对优势压倒别人，在个别团、营干部的默许","box":[[173,1208],[1089,1206],[1089,1236],[173,1238]]},{"text":"下，在比赛前，从二连抽出了四名军体骨干，顶替本连的几个弱手。尽管事情进行得很“秘","box":[[175,1239],[1092,1239],[1092,1272],[175,1272]]},{"text":"密”，但还是很快被人察觉并反映到上级去了……。作者就是用这种剥核桃的方法一步步地","box":[[173,1272],[1092,1272],[1092,1305],[173,1305]]},{"text":"引人人胜，回答了导语中提出的问题。","box":[[177,1305],[552,1312],[552,1336],[177,1329]]},{"text":"再看《华主席同代表们共商国家大计》中有一段是这样写的：“一位男女老少都喜爱的","box":[[220,1338],[1093,1340],[1093,1370],[220,1368]]},{"text":"相声演员正在发言，他一抬头，看见华主席席走进会场，并在他的对面就坐了。别看这位演","box":[[176,1370],[1093,1374],[1093,1402],[176,1398]]},{"text":"员、语言学家平时语言流畅；现在却热泪盈眶，顿然语塞。华主席一眼认出这是侯宝林，就","box":[[176,1403],[1094,1408],[1094,1438],[176,1433]]},{"text":"伸出手同他亲切地握手，鼓励他讲下去。”这样写，不比一-上来就写侯宝林更能引人人","box":[[177,1435],[1094,1441],[1094,1471],[177,1465]]},{"text":"胜吗？","box":[[179,1471],[237,1471],[237,1492],[179,1492]]},{"text":"6","box":[[229,1546],[246,1546],[246,1567],[229,1567]]}],"dimensions":{"height":1754,"width":1241}}