{"ocr_results":[{"text":"3、江青欺骗毛主席和中央政治局的亲笔信节录","box":[[261,240],[841,240],[841,264],[261,264]]},{"text":"主称在幸的改治后多位用志","box":[[189,351],[641,353],[641,408],[188,406]]},{"text":"我在四月对七四路治向会饿上的自我批评芒不锅们。","box":[[269,444],[909,448],[909,498],[269,494]]},{"text":"结几次政治局会饿上园点們的拙评华助，思些陋勤很大","box":[[194,527],[922,533],[922,594],[193,589]]},{"text":"男立上一时转过年，经过思盐，我识为会试基本上开的好","box":[[195,617],[917,622],[917,676],[194,671]]},{"text":"政注局比细结了。","box":[[199,713],[569,719],[568,763],[198,756]]},{"text":"当我谬话到回人帮是了家观有在，我才遇识到散爱成了","box":[[234,819],[911,823],[911,877],[234,873]]},{"text":"张党中尖的宗派主义的可能，我才识识到为什么生希烂年涌到","box":[[178,902],[909,918],[908,979],[177,963]]},{"text":"今年，勿次之每，常弟名一个重大要则问琴，主第在则同号","box":[[176,991],[893,997],[893,1054],[175,1049]]},{"text":"上不谎步的。","box":[[171,1090],[372,1090],[372,1143],[171,1143]]},{"text":"25-","box":[[497,1440],[607,1440],[607,1472],[497,1472]]}],"dimensions":{"height":1529,"width":1142}}