{"ocr_results":[{"text":"宅案命革灵《8》","box":[[236,192],[784,188],[784,221],[236,225]]},{"text":"伍、《8.16》反革命通敌案情简介","box":[[201,279],[808,279],[808,320],[201,320]]},{"text":"自1967年8月16日至1968年11月20日，犯罪分子多次在南昌市投","box":[[139,380],[927,378],[927,405],[139,407]]},{"text":"寄反革命信件，内容极端反动，疯狂攻击无产阶级文化大革命，并叫","box":[[82,426],[926,425],[926,453],[82,454]]},{"text":"喊要为蒋匪帮效劳，又叫要实现“三民主义”。这是一个死心塌地","box":[[80,473],[928,471],[928,501],[80,503]]},{"text":"决心与人民为敌的现行反革命分子。其主要特征是：美","box":[[77,519],[933,508],[934,548],[77,559]]},{"text":"一、从犯罪分子信件中提到的“我是江西省某工厂青年工人，现","box":[[134,570],[928,565],[928,596],[134,600]]},{"text":"在20岁”，以及多次作案都在南昌市等情况来看，作案者可能是南昌","box":[[81,617],[926,617],[926,644],[81,644]]},{"text":"市某个工厂或企业单位青年工人中的反动分子。","box":[[80,664],[658,665],[658,692],[80,691]]},{"text":"二、从犯罪分子在信中暴露的“我是武装基干民兵”等情况来看，","box":[[137,712],[911,712],[911,739],[137,739]]},{"text":"作案者可能尚未被群众所识破，表面上伪装积极，要求进步，实际上","box":[[79,759],[928,757],[928,786],[79,788]]},{"text":"是极端反动的分子。","box":[[78,806],[312,806],[312,836],[78,836]]},{"text":"三、从犯罪分子黑信中的内容和某些情节来看，作案者具有收音","box":[[134,854],[929,854],[929,883],[134,883]]},{"text":"机或能接触收音机经常偷听敌台广播，被蒋匪帮反动宣传所勾引而走","box":[[81,904],[928,904],[928,928],[81,928]]},{"text":"上犯罪道路。","box":[[79,949],[226,949],[226,980],[79,980]]},{"text":"四、犯罪分子书写水平不高，词句不够通顺，字体潦草，笔划较","box":[[137,998],[928,998],[928,1025],[137,1025]]},{"text":"活，但不老练。据此分析，作案者可能具有高小或初中左右的文化水","box":[[81,1041],[929,1045],[929,1076],[81,1072]]},{"text":"##大##","box":[[90,1287],[572,1307],[569,1358],[88,1337]]},{"text":"下","box":[[558,1288],[910,1288],[910,1342],[558,1342]]},{"text":"·11·","box":[[842,1436],[886,1436],[886,1458],[842,1458]]}],"dimensions":{"height":1553,"width":1043}}