{"ocr_results":[{"text":"永胜和江青作斗争那是很了不得的事情。我举个例子。黄永胜是我","box":[[210,236],[1333,240],[1333,274],[210,270]]},{"text":"从小就非常敬爱的一个老将军。我父亲是政治干部，黄永胜是军事","box":[[213,321],[1332,324],[1332,358],[213,355]]},{"text":"干部，但我父亲诚恳地说：“黄永胜政治水平比我高。”他说黄是一","box":[[211,406],[1329,408],[1329,442],[211,440]]},{"text":"个政治性、原则性很强的干部，非常守纪律，对工作认真。“9·13”","box":[[211,489],[1333,493],[1333,527],[211,523]]},{"text":"之后说我们销毁黑材料，我们销毁什么黑材料了，就是销毁了和林","box":[[213,575],[1332,578],[1332,612],[213,609]]},{"text":"彪照的照片。家里连个保险柜都没有，哪里来什么黑材料呀！春光","box":[[212,658],[1333,661],[1333,695],[212,692]]},{"text":"是黄总长的大儿子，他也是在非常重要的岗位上工作，但他根本就","box":[[213,743],[1333,745],[1333,779],[213,777]]},{"text":"不知道“9·13”。‘","box":[[212,828],[567,828],[567,865],[212,865]]},{"text":"“9·13”时，黄、吴、李、邱和他们的孩子都","box":[[551,829],[1331,829],[1331,863],[551,863]]},{"text":"在岗位上，就我一个人不在，因为当时我夫人在生小孩。如果要密","box":[[212,912],[1332,912],[1332,946],[212,946]]},{"text":"谋搞“9·13”的话，那黄、吴、李、邱等人也得准备点东西带走吧，","box":[[212,996],[1326,997],[1326,1031],[212,1030]]},{"text":"但却根本没有任何动作。我父亲他们认为，如果林不走，什么事都","box":[[213,1082],[1333,1082],[1333,1115],[213,1115]]},{"text":"没有，什么事都可以说得清，他这一走，什么事都说不清了。","box":[[212,1162],[1212,1164],[1212,1202],[212,1200]]},{"text":"6月29日下午：","box":[[209,1332],[459,1332],[459,1369],[209,1369]]},{"text":"李德：研究林彪，首先要研究他是一位什么样的人物。林彪在中","box":[[270,1417],[1330,1417],[1330,1451],[270,1451]]},{"text":"国历史上是一个特殊的人物，有许多特殊贡献。我接触林彪5年，","box":[[213,1499],[1311,1500],[1311,1537],[213,1536]]},{"text":"我认为他是一位统帅，也是一位学者。我就拿一年的事来说一说为","box":[[210,1584],[1330,1583],[1330,1620],[210,1621]]},{"text":"什么讲林是一位学者。","box":[[211,1670],[568,1670],[568,1704],[211,1704]]},{"text":"当国防部长几个月后，1960年1月份他读《列宁全集》36册，","box":[[276,1753],[1310,1752],[1310,1790],[276,1791]]},{"text":"从头到尾，核心题目是：战争不可避免的理论。因为当时我们党正","box":[[211,1838],[1332,1836],[1332,1874],[211,1876]]},{"text":"和赫鲁晓夫展开论战，战争与和平问题是主题。他自己看，也让我","box":[[208,1924],[1333,1921],[1333,1959],[208,1962]]},{"text":"帮他搞，凡是列宁有关帝国主义就是战争的理论全搞出来，不怕重","box":[[208,2010],[1332,2007],[1332,2045],[208,2048]]},{"text":"12","box":[[758,2131],[785,2131],[785,2159],[758,2159]]}],"dimensions":{"height":2263,"width":1560}}