{"ocr_results":[{"text":"到无产阶级手中”一句。","box":[[161,232],[392,232],[392,253],[161,253]]},{"text":"四、在第二大卫分第二段，概括中国赫鲁晓夫的三次讲话时，姚曾加上“总其一点，是","box":[[206,266],[1064,264],[1064,285],[206,287]]},{"text":"赤裸裸地主张资产阶级‘自由化””，之后陈又加上了一句：“为全国右派的猖狂进攻鸣锣","box":[[161,299],[1064,296],[1064,318],[161,321]]},{"text":"开辽”。（注：这句话在发表时，在“总其一点”之后还加上“是反对毛主席的无产阶级新","box":[[162,334],[1063,331],[1063,351],[162,354]]},{"text":"闻路线”）","box":[[164,369],[261,369],[261,387],[164,387]]},{"text":"五、在第二大节分第三段，批中国赫鲁晓夫说新华社应该“民办”，不要“官办”时，","box":[[205,400],[1050,396],[1050,419],[205,423]]},{"text":"陈（也可能是姚）加了一段：“官办”者，即无产阶级专政。中国赫鲁晓夫认为无产阶级专","box":[[160,433],[1062,431],[1062,453],[160,455]]},{"text":"政使资产阶级新闻路线受到“束缚”，要求有反对无产阶级专政、复辟资本主义的“自由”。","box":[[160,467],[1052,464],[1052,486],[160,489]]},{"text":"六、在第二大卫分第八段，即批判中国赫鲁晓夫关于报纸上“应该有几种不同的忌见”","box":[[204,499],[1053,497],[1053,518],[204,520]]},{"text":"一段中，文引！了毛主席关于舆论一律和列宁在《<火星报》编辑卫声明》的一段话之后，","box":[[160,534],[1049,531],[1049,551],[160,554]]},{"text":"陈或姚加了一段：“无产阶级的报纸，必须旗帜鲜明的同形形色色反马克息列宁主义、反毛","box":[[160,568],[1063,565],[1063,585],[160,588]]},{"text":"泽东思想的反动阶级、反动流派、反动思潮作斗争，不进行这种斗争，无产阶级报纸就会丧","box":[[160,601],[1062,599],[1062,619],[160,621]]},{"text":"失自己革命的灵魂。”","box":[[161,634],[375,633],[375,654],[161,655]]},{"text":"?","box":[[938,633],[947,633],[947,645],[938,645]]},{"text":"七、在第三大卫分第七段叙述《燕山夜话》一类专栏的作者队伍时，文中说：“那些叛","box":[[204,668],[1063,665],[1063,688],[204,691]]},{"text":"徒、特务，‘三教九流”，牛鬼蛇神…·成了中国赫鲁晓夫及其代理人的坐上宾”。陈伯达","box":[[159,701],[1061,699],[1061,720],[159,722]]},{"text":"把“坐上宾”改为“反革命打手”。","box":[[159,734],[505,734],[505,754],[159,754]]},{"text":"八、把第五大卫分第一段叙述文化大革命前夕时的一段文全节删掉，改成：文化大革","box":[[204,767],[1061,766],[1061,786],[204,787]]},{"text":"命“猛烈地炸开了中国赫鲁晓夫及其代理人把持的新闻界的反革命独立王国”。","box":[[158,798],[939,799],[939,823],[158,822]]},{"text":"儿、在第五大节分第三段姚加的“那些放毒、造谣的旧报纸，一个一个被封了，被革命","box":[[201,831],[1062,828],[1062,855],[201,858]]},{"text":"派夺了权”一句中，陈又在“那些”之后，加上“什么《羊城晚报》、《南方日报》之类”；","box":[[158,867],[1048,867],[1048,890],[158,890]]},{"text":"在“被封了”之后，加上“被冲了”三字。","box":[[158,902],[572,902],[572,922],[158,922]]},{"text":"十、在第五大节分第四段四条“经验教训”中陈歪段歪段地加了大男文字。","box":[[203,936],[934,934],[934,954],[203,956]]},{"text":"在第一条，坚定不移、始终一贯地二传毛泽东思想一段中，陈加了下列内容：","box":[[203,970],[957,969],[957,989],[203,990]]},{"text":"1、“二传毛泽东思想必须准确。”","box":[[204,1002],[552,1000],[552,1023],[204,1026]]},{"text":"2、“特别对于那种打着‘红旗”反红旗的卑鄙作法”。","box":[[204,1034],[754,1035],[754,1059],[204,1058]]},{"text":"3、“封锁毛主席的声音，这是所有反革命参正主义分子共同的卑鄙手段，我们的报纸","box":[[207,1070],[1059,1070],[1059,1090],[207,1090]]},{"text":"必须坚决反其边而行之。这样，报纸就能高高举起毛泽东思想伟大红旗，在各个时期十分鲜","box":[[158,1102],[1060,1102],[1060,1125],[158,1125]]},{"text":"明地为广大革命群众指出斗争的方向。”","box":[[156,1134],[552,1133],[552,1157],[156,1158]]},{"text":"“之传毛泽东思想，必须坚持同一切反马克思列宁主义、反毛泽东思想的反动思想进行","box":[[212,1166],[1059,1168],[1059,1191],[212,1189]]},{"text":"针锋相对的斗争。在当前，我们要继续尸开对国际上现代参正主义的大揭露、大批判。要进","box":[[156,1200],[1059,1202],[1059,1225],[156,1223]]},{"text":"一步批判中国赫鲁晓夫反革命参正主义路线，批判反动的资产阶级“多中心论”，批判山头","box":[[156,1235],[1058,1235],[1058,1258],[156,1258]]},{"text":"主义、宗派主义、个人主义和资产阶级反动世界观的各种表现，批判一切反无产阶级的反动","box":[[156,1267],[1057,1267],[1057,1291],[156,1291]]},{"text":"观点。破字当头，立在其中。毛泽东思想就是同形形色色资产阶级反动思想斗争中发尸起来","box":[[155,1302],[1057,1301],[1057,1324],[155,1325]]},{"text":"的。”","box":[[154,1337],[213,1334],[214,1356],[155,1359]]},{"text":"在第二条，报纸是阶级斗争的工贝一段的末尾，陈加了-一段：“要注忌人是会变的，必","box":[[200,1368],[1057,1370],[1057,1393],[200,1391]]},{"text":"须经常洗那些腐化分子，不让他们掌握报纸、新闻的工贝。”","box":[[156,1403],[779,1403],[779,1427],[156,1427]]},{"text":"在第三条，把新闻界两条路线斗争进行到底一段中，陈加了下百一段：","box":[[199,1436],[884,1437],[884,1461],[199,1460]]},{"text":"在当前，“除了从历史上全百批判资产阶级新闻路线外，要特别注总批判那种把新闻工","box":[[199,1470],[1057,1471],[1057,1495],[199,1494]]},{"text":"贝当作为某一资产阶级、小资产阶级派别服务的极端错误的作法。各地报纸、电台等等必须","box":[[155,1502],[1057,1507],[1057,1531],[155,1526]]},{"text":"3","box":[[992,1555],[1006,1555],[1006,1572],[992,1572]]}],"dimensions":{"height":1754,"width":1241}}