{"ocr_results":[{"text":"意，她准备第二天还要开，要陈永贵同志发言，她来出题目。陈永","box":[[206,322],[1036,321],[1036,348],[206,349]]},{"text":"贵同志说：“我发言就从老少组讲起，要讲和刘少奇斗争，和李雪","box":[[206,374],[1034,373],[1034,397],[206,398]]},{"text":"峰斗争。要讲大寨是怎样同资本主义修正主义斗争的体会，不需要","box":[[204,423],[1036,422],[1036,448],[204,449]]},{"text":"再出题目，大寨斗争经验题目有的是。”江说那也算，你讲你的，","box":[[204,472],[1022,472],[1022,499],[204,499]]},{"text":"但别的人由我来出题。由此可见，江青搞的所谓批邓，只不过是个","box":[[205,524],[1034,523],[1034,547],[205,548]]},{"text":"幌子，实际是她划框定调，她出题，别人答卷，以达到她不可告人","box":[[205,575],[1033,574],[1033,598],[205,599]]},{"text":"的目的。只是因为五日晚中央来电话催她急回，：这次会才没有开","box":[[205,626],[1033,626],[1033,650],[205,650]]},{"text":"成。要按她所出的题是很难答的。","box":[[206,677],[619,677],[619,701],[206,701]]},{"text":"宣扬封、资、修文艺","box":[[477,752],[764,750],[764,777],[477,779]]},{"text":"江青两次来大寨，每次都带着两大卡车电影片。她看的是《断","box":[[262,827],[1033,827],[1033,851],[262,851]]},{"text":"桥》、《打金枝》、《红娘》。西方影片《斗牛》、《冷酷的心》、","box":[[205,878],[1019,878],[1019,902],[205,902]]},{"text":"《鸽子号》，还有一些诲淫诲盗的影片。她听的戏和音乐是《二进","box":[[209,928],[1030,928],[1030,952],[209,952]]},{"text":"宫》、《斩黄袍》、《斩子》、《白蛇传》、《空城计》等。不仅","box":[[204,979],[1032,977],[1032,1001],[204,1003]]},{"text":"自己看，自已听，还要请文艺界、新闻界的人看。去年九月，她让","box":[[206,1029],[1034,1029],[1034,1053],[206,1053]]},{"text":"名演员给大寨社员组织一次晚会，：演奏、演唱的节目，大部分是帝","box":[[204,1080],[1032,1080],[1032,1103],[204,1103]]},{"text":"王将相，才子佳人，妄图利用这些封资修毒素，毒害大寨人的灵","box":[[202,1130],[1030,1129],[1030,1153],[202,1154]]},{"text":"魂，玷污大寨红旗。她在吃饭时或是让她叫来的“艺术家”吹奏演","box":[[202,1179],[1032,1178],[1032,1205],[202,1206]]},{"text":"唱作乐，或是播放旧京剧，旧昆曲等唱片，她还情不自禁地手舞足","box":[[204,1230],[1029,1230],[1029,1254],[204,1254]]},{"text":"蹈，随声和唱，真是丑态百出。","box":[[204,1281],[589,1281],[589,1305],[204,1305]]},{"text":"贵族老爷态度","box":[[482,1356],[758,1356],[758,1387],[482,1387]]},{"text":"江青去年九月来大寨时，要陈永贵、王谦同志陪同她骑马上虎","box":[[260,1433],[1033,1433],[1033,1457],[260,1457]]},{"text":"头山。王谦同志如实告她：．“我不骑马，可以步行陪你上山。”不","box":[[201,1482],[1034,1480],[1034,1507],[201,1509]]},{"text":"·8·","box":[[226,1533],[277,1530],[278,1553],[228,1556]]}],"dimensions":{"height":1754,"width":1241}}