{"ocr_results":[{"text":"第","box":[[1123,243],[1183,243],[1183,273],[1123,273]]},{"text":"页","box":[[1265,245],[1295,245],[1295,273],[1265,273]]},{"text":"一个丝成分。在发文够如交之放的识.至提工他的及要之路","box":[[223,345],[1346,348],[1346,411],[223,408]]},{"text":"经人改天多的。车旧红：距意证久呢报重政1","box":[[220,459],[1367,464],[1367,524],[220,519]]},{"text":"活关。这么结丝之言，是的这品经生在过，在付战所呢的即此多重","box":[[217,559],[1357,570],[1356,640],[216,630]]},{"text":"结线的思点到的了右层的我主没来化的。","box":[[217,666],[991,676],[990,747],[216,738]]},{"text":"月日多宣把今争，手里写","box":[[310,789],[1372,794],[1372,855],[310,849]]},{"text":"装","box":[[101,858],[125,858],[125,950],[101,950]]},{"text":"主学算我跑作作会，生此动，的一直遍主多红导旧去","box":[[214,887],[1341,898],[1340,969],[213,958]]},{"text":"北京市电车公司印刷厂出品七八·一","box":[[60,925],[87,925],[83,1273],[56,1273]]},{"text":"张轻休：寻救尽抒的顶她坟后《阳学，们去管去生","box":[[214,998],[1335,1007],[1335,1070],[214,1062]]},{"text":"芒崔多我出生里伤，机主见志.是时甚何为对","box":[[213,1101],[1340,1112],[1339,1183],[212,1171]]},{"text":"世哦，的射也五出身理伤，过给。是过球的么去收水","box":[[226,1223],[1343,1229],[1343,1290],[226,1284]]},{"text":"线歌容","box":[[95,1255],[123,1255],[123,1346],[95,1346]]},{"text":"折角：乡此扭生他当放层挑的的望，红你在红作他吗","box":[[210,1326],[1334,1336],[1334,1399],[209,1390]]},{"text":"到回作全十的的你阳笑，多时忍，所多加全义履","box":[[218,1436],[1329,1446],[1329,1507],[217,1496]]},{"text":"他心先发主中故力育曲要的心多的我红经物、强袁”光","box":[[215,1542],[1354,1555],[1353,1622],[214,1608]]},{"text":"内在的差多改收”和所给学了改沉生民“之改段作”等文为评活。","box":[[206,1658],[1351,1663],[1351,1724],[206,1719]]},{"text":"会心、在么人的批改了他的的饭怎交，红油了我的是山人你","box":[[211,1762],[1334,1771],[1334,1842],[210,1833]]},{"text":"及是程到你是及你之待的事学了的，你在支持有以败","box":[[199,1862],[1420,1867],[1420,1938],[199,1933]]},{"text":"(1487)","box":[[259,1925],[325,1925],[325,1954],[259,1954]]}],"dimensions":{"height":2035,"width":1441}}