{"ocr_results":[{"text":"在实际工作中拨乱反正和探索新问题提供了新的精神武器。","box":[[80,45],[897,42],[897,68],[81,71]]},{"text":"它将在全党推动一个新的学习运动。办法是要将《决议》的学","box":[[84,99],[913,97],[913,124],[85,126]]},{"text":"习同马列主义、毛泽东思想的学习结合起来，同总结各个方","box":[[83,153],[912,152],[912,179],[83,180]]},{"text":"面的经验和各个人的经验结合起来。","box":[[81,210],[568,210],[568,234],[81,234]]},{"text":"人们创造历史的能力要在不断总结历史经验中得到提","box":[[137,263],[913,261],[913,287],[137,289]]},{"text":"高。我们中国人历来有总结历史经验的传统。共产党人更加","box":[[81,317],[914,317],[914,344],[81,344]]},{"text":"应当有总结历史经验并从中得到教益的自觉性。我们是在十","box":[[78,370],[915,368],[915,398],[79,400]]},{"text":"亿人口的大国从事社会主义建设，这是一项前无古人的事业，","box":[[80,428],[912,428],[912,451],[80,451]]},{"text":"没有现成的经验可资利用。我们自己的无论是成功的经验或","box":[[80,483],[912,483],[912,506],[80,506]]},{"text":"失败的经验，如果能加以正确的总结，都将是宝贵的财富。","box":[[79,537],[895,537],[895,561],[79,561]]},{"text":"因此，总结经验决不只是为了消除分歧，而是我们积极创造","box":[[78,590],[911,590],[911,616],[78,616]]},{"text":"历史的一种动力。","box":[[77,642],[308,644],[308,672],[76,670]]},{"text":"同时，在一个时代，一个历史时期，指导人们前进的精","box":[[135,700],[910,700],[910,726],[135,726]]},{"text":"神武器，不应当仅仅限于前人创造的理论成果，而且应当包","box":[[75,753],[911,754],[911,781],[75,780]]},{"text":"括这一代人在继承运用这些成果时所作出的新贡献，包括这","box":[[75,808],[909,809],[909,835],[75,834]]},{"text":"一代人加进这个精神宝库中的新东西。二十世纪初，列宁曾","box":[[76,863],[909,863],[909,890],[76,890]]},{"text":"向无产阶级文学工作者提出，要用社会主义无产阶级的经验","box":[[75,915],[909,916],[909,945],[75,944]]},{"text":"和生气勃勃的工作去丰富人类革命思想的最新成就，要使过","box":[[76,973],[909,973],[909,997],[76,997]]},{"text":"去的经验和现在的经验之间经常发生相互作用。列宁的这个","box":[[74,1026],[909,1027],[909,1054],[74,1053]]},{"text":"要求，不仅适用于文学工作，也是向无产阶级政党提出的一","box":[[73,1079],[905,1081],[905,1108],[73,1106]]},{"text":"项重大历史任务。这个任务，就是在马克思主义普遍真理指","box":[[75,1137],[905,1137],[905,1161],[75,1161]]},{"text":"导下，不断总结革命实践的新鲜经验，并把它上升为理论，","box":[[71,1187],[888,1188],[888,1218],[71,1217]]},{"text":"又反过来指导新的实践。","box":[[73,1245],[399,1245],[399,1272],[73,1272]]},{"text":"7","box":[[873,1297],[889,1297],[889,1320],[873,1320]]}],"dimensions":{"height":1332,"width":954}}