{"ocr_results":[{"text":"携坚定，工作积极。在工作队入村初期，只因对工你队提了发见，","box":[[65,132],[1038,126],[1038,172],[65,179]]},{"text":"被诬为破坏远动。陶铸师亲倒《顿关》，杨言安拔掉“杨家将》结果杨","box":[[62,177],[1048,175],[1048,221],[62,223]]},{"text":"我将三兄第和老母亲，还有一个在外工你的堂哥之也都人人过关，全","box":[[68,226],[1046,221],[1046,272],[68,276]]},{"text":"皮护斗。","box":[[77,291],[191,291],[191,319],[77,319]]},{"text":"陶在四波中忠实推行在实在的改动路线，致使广西四活地区运","box":[[133,331],[1040,334],[1040,371],[132,368]]},{"text":"动越才指越长，大五年一批了一年多才结束;千齐怨气较大，若逸症","box":[[62,379],[1046,374],[1046,421],[62,426]]},{"text":"不少。陶的恶英是鬓竹唯书。","box":[[70,430],[517,430],[517,470],[70,470]]},{"text":"鼓吹金钱挂帅，物质第一；反对突击政治","box":[[292,473],[879,480],[878,535],[291,528]]},{"text":"毛主席说：“政冶工作是一切工你的生命找的林同志说：“用毛泽","box":[[130,544],[1043,540],[1043,584],[131,588]]},{"text":"东思想武装走来的人，是最大的战斗力”、用毛净东思想教奇全体人风","box":[[67,596],[1046,594],[1046,634],[67,636]]},{"text":"是最好的战备。”","box":[[66,659],[288,645],[290,672],[67,686]]},{"text":"可是陶铸则衣其道而行之。购子关五年先后到百色、兴安、桂林","box":[[135,689],[1040,701],[1039,742],[134,730]]},{"text":"等地林壶二作，作了不少所谓“指示”，似完全是修正主义的一路货色","box":[[64,743],[1042,748],[1042,782],[64,777]]},{"text":"如他多次到桂林每析查的工作只有五：仰城市风景延设、卫生、交","box":[[58,785],[1038,792],[1038,838],[57,831]]},{"text":"通、生活，生产，从未桥查和布置学月它传无泽东恐想。根本水讲用","box":[[60,838],[1037,838],[1037,882],[60,882]]},{"text":"毛师东思想描乌工作。無到之处，总是站在资产所级老爷的立上任","box":[[61,895],[1037,894],[1037,931],[61,932]]},{"text":"意拙责群众。如他在面色说：“你们就是栽树，只会砍树，把百色变成","box":[[61,942],[1036,939],[1036,980],[61,983]]},{"text":"白色恐怖，!”《你愿吃三百多斤，你再抖稀、种稀一总我也赞成。你讲","box":[[56,987],[1036,989],[1036,1033],[56,1030]]},{"text":"你不吃粮食，你一株不拼也可处，喝西北风呀！","box":[[57,1036],[740,1038],[740,1074],[57,1073]]},{"text":"陶铸还大肆心扬他的物质第一的修正主义货色，大力推销他提击","box":[[124,1086],[1031,1087],[1031,1125],[124,1124]]},{"text":"的“平整土地，提高排，发爱畜收，广种级肥，大搭多种经营，大","box":[[58,1134],[1027,1140],[1027,1171],[58,1165]]},{"text":"推蓝林缓化”帕方纤。说什么“作为三线老方，除才抛水利更设楷好","box":[[58,1186],[1034,1195],[1034,1225],[58,1216]]},{"text":"把生产特好：带个样极，把耕作制度改变，加上社会主义教高工作之","box":[[55,1235],[1025,1236],[1025,1274],[55,1273]]},{"text":"外，再形是采取一个經济政策（柱：即三年征购次契政策）。“没有四","box":[[53,1285],[1028,1287],[1028,1327],[53,1325]]},{"text":"西片左右口粮，番生产高潮可从，但不可能惜根好，要指旋设后方大","box":[[52,1326],[1030,1332],[1030,1379],[51,1373]]},{"text":"规也不是很图的后方，因为肚寻吃不饱嘛！他对西色的同志说，故","box":[[51,1383],[1031,1385],[1031,1422],[51,1420]]},{"text":"变西色的面晚是：“你们一个四十机是四面斤口粮：五十元钱的最低","box":[[48,1428],[1033,1434],[1033,1474],[47,1468]]},{"text":"分配水平，再加上一个大造林，必是“面色，了。”更恶毒的是他还有恋","box":[[53,1475],[1026,1480],[1026,1521],[52,1516]]},{"text":"办林凡同忘美子“人的国素芳","box":[[51,1527],[473,1527],[473,1561],[51,1561]]},{"text":"一的英明花喝良调，说如果每一良民","box":[[469,1530],[1025,1535],[1025,1566],[468,1561]]},{"text":"3","box":[[531,1576],[552,1576],[552,1597],[531,1597]]}],"dimensions":{"height":1660,"width":1107}}