{"ocr_results":[{"text":"此等等。","box":[[68,40],[171,44],[170,73],[67,69]]},{"text":"《无产阶级专政时代的经济和政治》1919年10月30日。《列","box":[[361,93],[882,93],[882,113],[361,113]]},{"text":"宁选集》第4卷第93页","box":[[377,126],[590,126],[590,147],[377,147]]},{"text":"只有无产阶级才能成为彻底的民主主义者","box":[[232,259],[739,260],[739,283],[232,282]]},{"text":"只有无产阶级，才能成为一一而且按其阶级地位来说不能不成","box":[[130,336],[883,339],[883,363],[130,360]]},{"text":"为一一彻底的民主主义者，坚决反对专制制度的战士，而不会作任","box":[[73,385],[885,388],[885,414],[73,411]]},{"text":"何让步和妥协。只有无产阶级，才能成为争取政治自由与民主制度","box":[[70,437],[883,439],[883,463],[70,461]]},{"text":"的先进战士，因为第一，无产阶级受到的政治压迫最厉害，这个阶","box":[[74,488],[882,490],[882,513],[74,511]]},{"text":"级的地位不可能有丝毫改变，它既没有接近最高政权的机会，甚至","box":[[69,538],[884,540],[884,564],[69,562]]},{"text":"也没有接近官吏的机会，也无法影响社会舆论。第二，只有无产阶","box":[[73,589],[883,591],[883,614],[73,612]]},{"text":"级才能彻底实现政治制度和社会制度的民主化，因为实行这种民主","box":[[71,639],[884,641],[884,665],[71,663]]},{"text":"化，就会使工人成为这个制度的主人。","box":[[71,691],[540,691],[540,715],[71,715]]},{"text":"《俄国社会民主主义者的任务》1897年。《列宁选集》第","box":[[358,739],[884,739],[884,762],[358,762]]},{"text":"1卷第103页","box":[[378,773],[491,773],[491,794],[378,794]]},{"text":"不实现民主，社会主义就不能实现","box":[[270,923],[694,924],[694,947],[270,946]]},{"text":"不实现民主，社会主义就不能实现，这包括两个意思：（1）","box":[[127,995],[876,998],[875,1022],[127,1019]]},{"text":"无产阶级如果不在民主斗争中为社会主义革命做好准备，它就不能","box":[[71,1046],[881,1049],[881,1072],[71,1069]]},{"text":"实现这个革命；（2）胜利了的社会主义如果不实行充分的民主，","box":[[71,1096],[871,1099],[870,1122],[71,1119]]},{"text":"它就不能保持它所取得的胜利，引导人类走向国家的消亡。","box":[[69,1147],[796,1149],[796,1172],[69,1170]]},{"text":"《论对马克思主义的讽刺和“帝国主义经济主义”》1916","box":[[356,1194],[884,1195],[884,1218],[356,1217]]},{"text":"年8一10月。《列宁金集》第23卷第70页","box":[[373,1228],[764,1228],[764,1251],[373,1251]]},{"text":"12","box":[[87,1292],[115,1292],[115,1318],[87,1318]]}],"dimensions":{"height":1332,"width":954}}