{"ocr_results":[{"text":"子和、彭刘一小摄反草命修正主义分子，对我们健大领袖毛主席，","box":[[261,252],[1330,246],[1331,301],[262,306]]},{"text":"充满了刻骨仇恨，用最恶毒語言攻击毛主席，反对以毛主席为首的，无","box":[[267,315],[1330,323],[1329,360],[266,352]]},{"text":"产阶级司令部、毛主席的草命路，同时吹捧中国赫鲁曉夫~～刘少","box":[[274,378],[1308,386],[1308,421],[274,412]]},{"text":"奇，把彭捧得很高，企图复辟资本主义。","box":[[264,441],[896,444],[896,478],[264,475]]},{"text":"2、彭一伙把毛泽东思想视如洪水猛兽，疯狂的攻击广大工农","box":[[337,504],[1297,510],[1297,544],[337,538]]},{"text":"兵群众。学习毛著，“是买卖婚姻，勉强溪合”。大力贩卖前发刊","box":[[275,564],[1309,571],[1309,608],[275,602]]},{"text":"词和黑修养介级斗零盖子。明回摄胆地包底地、富、反、杯，打专食","box":[[273,621],[1311,630],[1310,687],[272,678]]},{"text":"3、彭真一伙疯狂反对毛主席关于价级矛盾、阶级斗手的学，","box":[[348,692],[1292,695],[1292,730],[348,726]]},{"text":"鼓吹阶级調和论。企图和平演变。","box":[[281,755],[767,755],[767,789],[281,789]]},{"text":"资本主义道路当权派州少青的支","box":[[823,760],[1304,758],[1304,795],[823,797]]},{"text":"4、彭反草命集团与党内最大走资本主义当权派刘少奇，狼","box":[[349,815],[1307,819],[1307,856],[349,852]]},{"text":"为奸，结成一伙打着无产阶级专政的旗号，实行资产阶级专政，压制","box":[[281,878],[1310,883],[1310,917],[281,913]]},{"text":"打击革命干部，对资产阶级反动学术权威等施仁政。鼓吹国家职能消","box":[[278,941],[1307,945],[1307,979],[278,975]]},{"text":"灭论。说无产阶级专政，該进博物馆了。用来了，#们人经在。心习","box":[[274,1000],[1305,1007],[1305,1048],[274,1040]]},{"text":"5、彭一伙反草命修正主义集团，鼓吹资产阶级专政，企图题","box":[[345,1066],[1310,1070],[1310,1105],[345,1101]]},{"text":"复无产阶级专政，作奥准备，利用前发刊词，利用各种宣传障地，","box":[[284,1127],[1336,1134],[1335,1168],[284,1161]]},{"text":"宣传工具，大造奥，为复辟资本主义大开灯。主文水平。残花","box":[[279,1187],[1317,1197],[1316,1234],[279,1225]]},{"text":"6、彭宾一伙在工交、财、农业等各条战上大力推行，反草","box":[[346,1254],[1306,1258],[1306,1292],[346,1288]]},{"text":"命修正主义路线。搞物质刺激，实行钞票挂帅，为复辟资本主义开方","box":[[286,1313],[1314,1319],[1314,1356],[286,1350]]},{"text":"便之門。","box":[[279,1374],[404,1374],[404,1417],[279,1417]]},{"text":"7、彭一伙反草命修正主义分子推行反革命组织路鐵，招降纳","box":[[362,1439],[1318,1444],[1318,1481],[362,1476]]},{"text":"叛，结党营私，网罗牛鬼蛇神，对以毛主席为首的党中央进行严密封","box":[[286,1502],[1315,1507],[1315,1542],[286,1536]]},{"text":"镇。使北京成为针插不进、水泼不进的独立王国。定资本主义的","box":[[288,1563],[1312,1569],[1312,1605],[288,1599]]},{"text":"8、彭一伙反草命修正主义分子疯狂地反对三面红旗，企图为","box":[[346,1626],[1303,1630],[1303,1664],[346,1660]]},{"text":"彭德怀翻案，六一年策划了惊心动魄的畅观楼事件。","box":[[280,1689],[1055,1691],[1055,1725],[280,1724]]},{"text":"9、彭一伙反对毛主席提出的无产阶级教育方針，反对知识分","box":[[349,1750],[1300,1754],[1300,1788],[349,1784]]},{"text":"~3~","box":[[763,1815],[869,1815],[869,1850],[763,1850]]}],"dimensions":{"height":1932,"width":1590}}