{"ocr_results":[{"text":"第三八九條军事法庭所理的案件不得提起附帶民事。軍事法庭於理案件時，知悉共和","box":[[80,133],[109,133],[113,1054],[84,1054]]},{"text":"第三八八條","box":[[161,135],[185,135],[185,253],[161,253]]},{"text":"第三八七條","box":[[316,135],[341,135],[341,249],[316,249]]},{"text":"第三八六條","box":[[471,134],[495,134],[495,248],[471,248]]},{"text":"第三八五條","box":[[626,135],[651,135],[651,249],[626,249]]},{"text":"除（一九二三年七月十日一法合棠福第四八號，法合第四八○號一）。（因本條","box":[[160,241],[190,241],[190,1054],[160,1054]]},{"text":"共和國查機及機關對於配置省法院的查員（：即主任查員），就其","box":[[470,262],[496,262],[499,1053],[473,1053]]},{"text":"國或私人因犯罪受有損害和損失時，得於判决時對於將來的民事得探取保全方","box":[[43,265],[70,265],[73,1051],[46,1051]]},{"text":"已為第一一九條至第一二一條一所吸收，故予除。）","box":[[121,265],[148,265],[150,794],[123,794]]},{"text":"其将案件移交該管值查員，而區人民查員對於此项命合必遵守。","box":[[199,266],[226,266],[228,916],[201,916]]},{"text":"一人對於該案進行查。检察長應同時通知區人民值查員不再續辨理此案，命","box":[[238,268],[266,268],[267,1054],[239,1054]]},{"text":"告後，得將案件移轉配置於省法院的值查員，於此時命合配置於省法院的查員","box":[[279,264],[302,264],[303,1050],[280,1050]]},{"text":"配置於省法院的检察長，接到區人民查員於就省法院管的案件開始查的報","box":[[314,264],[344,264],[345,1052],[315,1052]]},{"text":"實施值查行為。","box":[[355,267],[379,267],[381,416],[357,416]]},{"text":"限制，如持有省法院院長及配置於省法院的检察長的名明書，得於全蘇俄境内","box":[[393,265],[419,265],[421,1050],[395,1050]]},{"text":"處理案件所為的處分和命合均應遵守。配置於省法院的查員不受自己管辖區域的","box":[[432,265],[460,265],[462,1051],[434,1051]]},{"text":"行全部值查或個别的值查行為。","box":[[511,266],[535,266],[535,566],[511,566]]},{"text":"（刑事法典第一O九條），检察長如不同意查員的處分時，得指示查員進","box":[[549,268],[573,268],[575,1050],[551,1050]]},{"text":"時，得承查文書有查文書的效力，不再進行查或進行個别的查行為","box":[[584,261],[614,261],[617,1052],[587,1052]]},{"text":"配置於省法院的查員，如因案件已臻明瞭或因被告人自白犯罪已无需進行查","box":[[625,262],[652,262],[654,1053],[627,1053]]},{"text":"察長督的察員辨理。","box":[[663,266],[688,265],[691,499],[667,499]]},{"text":"100","box":[[609,1076],[643,1074],[644,1089],[611,1091]]}],"dimensions":{"height":1172,"width":764}}