{"ocr_results":[{"text":"第三一八條除（九二四年十月十六日一一九二四年法合第七八號，法合第七八四","box":[[64,139],[94,139],[97,1062],[66,1062]]},{"text":"第三一七條","box":[[146,141],[171,141],[171,262],[146,262]]},{"text":"第三一六條","box":[[340,142],[365,142],[365,256],[340,256]]},{"text":"第三一五條","box":[[494,142],[519,142],[519,257],[494,257]]},{"text":"第三一四條","box":[[650,142],[674,142],[674,258],[650,258]]},{"text":"第二四章判决","box":[[202,227],[237,227],[234,463],[199,463]]},{"text":"判庭的書記員及其他人員，於時均不得出席室。","box":[[107,271],[134,271],[133,817],[106,817]]},{"text":"参興本案判的判員，才能出席室，參加及製作判决。候補判員、公","box":[[146,270],[173,270],[173,1066],[146,1066]]},{"text":"卷宗一供送出，以便依普通程序進行值查、起和判","box":[[265,275],[288,275],[288,805],[265,805]]},{"text":"其控罪行時，法院應停止本案的判，将本案受蕃人及新被之人連同全部","box":[[300,271],[328,271],[329,1060],[301,1060]]},{"text":"如新控的罪行與本案對受人已控的罪行有密切聯系，而不能與本案分","box":[[339,270],[366,270],[368,1060],[341,1060]]},{"text":"此時法院對於已被检之人得探用强制處分。","box":[[377,273],[403,273],[405,711],[379,711]]},{"text":"將其送出以便依普通程序進行查、起和判，将此點向被检人宣示。","box":[[417,275],[444,275],[444,1051],[417,1051]]},{"text":"即於取其意見後，即以附有理由的裁定加以，此後，即使此案與本案分","box":[[456,274],[479,274],[482,1041],[458,1041]]},{"text":"法院在公判中發現有未經作為受人而加以检的犯罪人時，如梭察長已經出庭，","box":[[492,270],[520,270],[522,1047],[494,1047]]},{"text":"時法院對於已被的人，得探用强制處分。","box":[[534,276],[558,276],[558,733],[534,733]]},{"text":"人宣示，使與本案分將其送出，以便依普通程序進行查、起和判。此","box":[[569,272],[599,272],[600,1062],[570,1062]]},{"text":"有察長出庭，於取其意見後，即以附有理由的裁定检該人，而將此向","box":[[609,273],[637,273],[638,1062],[610,1062]]},{"text":"法院發現某一人的陳係偽時，於可能圖内將其陳远逐字逐句記人筆錄，如","box":[[651,275],[674,275],[674,1061],[651,1061]]},{"text":"如變更原控而處刑不加重時，法院應續判，依據新的控内容予以判决。","box":[[688,276],[715,276],[715,1051],[688,1051]]},{"text":"83","box":[[125,1082],[146,1082],[146,1099],[125,1099]]}],"dimensions":{"height":1172,"width":764}}