{"ocr_results":[{"text":"到底，党的组织和党所领导的群众发生隔离”。陈云同志一","box":[[53,41],[895,41],[895,70],[53,70]]},{"text":"九四二年十一月在西北局高千会上关于整党问题的长篇发言","box":[[54,95],[895,95],[895,125],[54,125]]},{"text":"中，有一节是专门讲反对自由主义的。他在讲到自由主义的","box":[[52,150],[895,147],[895,177],[52,180]]},{"text":"实质和危害时指出，“自由主义的实质是什么？我看实际上","box":[[52,204],[895,204],[895,234],[52,234]]},{"text":"是助长了错误，是给坏的东西、坏的人起了助长的作用。这","box":[[51,259],[897,258],[897,287],[51,288]]},{"text":"种错误思想，对干部十分不利，它不能起到教育作用，而只","box":[[54,314],[895,314],[895,341],[54,341]]},{"text":"能损害人、损害党。”在我们的生活中，自由主义的腐蚀作","box":[[52,367],[895,368],[895,397],[52,396]]},{"text":"用是很明显的。在一些单位存在的工作拖拉，纪律松弛，党","box":[[57,423],[895,423],[895,450],[57,450]]},{"text":"的路线得不到认真贯彻，同志关系不和谐，歪风邪气抬头等","box":[[55,478],[897,478],[897,504],[55,504]]},{"text":"现象，都同自由主义的存在有很大关系。一些党组织之所以","box":[[51,531],[895,529],[895,559],[51,561]]},{"text":"存在涣散软弱状态，自由主义也是一个重要的原因。","box":[[52,586],[781,587],[781,613],[52,612]]},{"text":"批评与自我批评是我们党的三大作风之一，是提高思想、","box":[[117,641],[897,641],[897,668],[117,668]]},{"text":"增强团结、改进工作的有效武器。自由主义却取消批评和斗","box":[[56,696],[897,696],[897,722],[56,722]]},{"text":"争。我们队伍里存在的许多矛盾，本来都可以通过批评与自","box":[[54,748],[894,749],[894,777],[54,776]]},{"text":"我批评得到解决。但是，在有些地方，批评与自我批评就是","box":[[54,805],[896,805],[896,832],[54,832]]},{"text":"开展不起来。有的人一听到批评意见，就反感，就抵制，就","box":[[55,859],[897,859],[897,886],[55,886]]},{"text":"反对，甚至暴跳如雷。还有一些人是面对错误言论和歪风邪","box":[[54,912],[897,913],[897,940],[54,939]]},{"text":"气，不敢进行批评，或者不能理直气壮地进行批评。在这里，","box":[[53,964],[897,965],[897,996],[53,995]]},{"text":"通行的是自由主义。因此，要恢复批评与自我批评的优良作","box":[[53,1019],[896,1020],[896,1051],[53,1050]]},{"text":"风，一定要下决心克服自由主义。","box":[[55,1073],[516,1076],[516,1106],[55,1103]]},{"text":"对某些不良现象，如果采取自由主义态度，不教育，不","box":[[112,1130],[897,1129],[897,1159],[112,1160]]},{"text":"批评，撒手不管，任其发展，就会变成严重的问题。对一个","box":[[53,1183],[895,1184],[895,1214],[53,1213]]},{"text":"党员和干部的错误，如果不严肃地进行批评教育，而是采取","box":[[54,1238],[896,1236],[896,1270],[54,1272]]},{"text":"3","box":[[861,1291],[880,1291],[880,1317],[861,1317]]}],"dimensions":{"height":1332,"width":954}}