{"ocr_results":[{"text":"和社会帝国主义侵略的需要，是逐步提高人民物质生活和","box":[[56,165],[848,164],[849,195],[56,196]]},{"text":"文化生活水平的需要，从长远来说，也是逐步缩小三大差","box":[[56,226],[847,225],[848,256],[56,257]]},{"text":"别，为过渡到共产主义社会准备物质条件的需要。生产力","box":[[54,286],[846,284],[847,314],[54,316]]},{"text":"是最革命的因素。在无产阶级专政下，上层建筑和生产关","box":[[54,347],[847,347],[847,377],[54,377]]},{"text":"系领域之所以还要继续革命，归根到底，是生产力发展的","box":[[53,408],[848,406],[849,435],[53,438]]},{"text":"要求。上层建筑和生产关系的变革，又反过来为生产力的","box":[[51,467],[846,465],[847,495],[51,497]]},{"text":"发展开辟道路。义主大","box":[[52,527],[422,527],[422,557],[52,557]]},{"text":"粉碎“四人帮”以来全国经济形势的发展，深刻说","box":[[110,587],[848,585],[849,615],[111,617]]},{"text":"明，抓住揭批“四人帮”这个伟大的阶级斗争，抓住学大","box":[[48,646],[847,644],[848,677],[48,679]]},{"text":"庆、学大寨的伟大革命群众运动，能够发生多么巨大的威","box":[[49,708],[847,706],[848,736],[49,739]]},{"text":"力。我们一定要把揭批“四人帮”的斗争同学大庆、学大","box":[[48,766],[846,765],[847,799],[48,800]]},{"text":"寨的群众运动更紧密地结合起来，更深入地开展起来，独","box":[[48,828],[845,826],[846,857],[48,859]]},{"text":"立自主，自力更生，艰苦奋斗，勤俭建国，备战、备荒、","box":[[46,888],[828,888],[828,918],[46,918]]},{"text":"为人民，把国民经济搞上去。我们要奋战几年，按照原定","box":[[47,948],[844,947],[845,978],[47,979]]},{"text":"规划，按照大庆式企业和大寨县的标准，在第五个五年计","box":[[46,1011],[843,1008],[844,1037],[46,1040]]},{"text":"划期内，把全国三分之一的企业建成大庆式企业，三分之","box":[[47,1069],[840,1066],[841,1097],[47,1100]]},{"text":"一的县建成大寨县。做到这一步，我国社会主义制度就将","box":[[43,1129],[842,1127],[843,1158],[43,1160]]},{"text":"大为巩固，社会主义经济也将大为繁荣。","box":[[44,1190],[599,1188],[600,1219],[44,1221]]},{"text":"保卫社会主义公有制，粉碎城乡资本主义势力的进","box":[[107,1250],[841,1248],[842,1279],[108,1281]]},{"text":"攻，是一场严重的斗争。几年来，在“四人帮”支持和包","box":[[45,1312],[841,1307],[842,1338],[45,1342]]},{"text":"-51-","box":[[757,1376],[811,1376],[811,1390],[757,1390]]}],"dimensions":{"height":1467,"width":964}}