{"ocr_results":[{"text":"53","box":[[871,5],[920,5],[920,41],[871,41]]},{"text":"的领导，巩固无产阶级专政，为社会主义经济基础服务，","box":[[48,164],[822,163],[822,194],[48,195]]},{"text":"而决不是要削弱以至破坏党的领导和无产阶级专政，削弱","box":[[48,225],[846,223],[847,254],[48,256]]},{"text":"以至破坏社会主义经济基础。","box":[[50,286],[440,286],[440,316],[50,316]]},{"text":"#果装电热联限面东谷宝社","box":[[461,282],[846,284],[845,313],[461,311]]},{"text":"为了健全民主集中制，还必须坚决反对一切无组织无","box":[[107,345],[849,344],[850,375],[107,376]]},{"text":"纪律的行为，重申党的纪律：（一）个人服从组织；（二）","box":[[46,406],[839,404],[840,433],[46,436]]},{"text":"少数服从多数；（三）下级服从上级；（四）全党服从中","box":[[45,465],[846,465],[846,495],[45,495]]},{"text":"央。要用三大纪律八项注意教育战士，教育干部，教育群","box":[[46,525],[848,525],[848,555],[46,555]]},{"text":"众，教育党员和人民。","box":[[46,585],[342,585],[342,615],[46,615]]},{"text":"毛主席说：“我们的目标，是想造成一个又有集中又","box":[[104,642],[848,644],[847,677],[104,675]]},{"text":"有民主，又有纪律又有自由，又有统一意志、又有个人心","box":[[45,704],[846,705],[845,736],[45,734]]},{"text":"情舒畅、生动活泼，那样一种政治局面，以利于社会主义","box":[[44,763],[846,764],[845,795],[44,794]]},{"text":"革命和社会主义建设，较易于克服困难，较快地建设我国","box":[[44,823],[847,825],[846,856],[44,854]]},{"text":"的现代工业和现代农业，党和国家较为巩固，较为能够经","box":[[44,882],[847,886],[846,917],[44,913]]},{"text":"受风险。”我们要用毛泽东思想统一全党全军和全国各族","box":[[43,943],[844,946],[843,977],[43,974]]},{"text":"人民的认识，健全民主集中制，实现毛主席所倡导的这种","box":[[44,1003],[843,1006],[842,1037],[44,1033]]},{"text":"政治局面。防#","box":[[39,1060],[326,1058],[326,1096],[39,1098]]},{"text":"第八，一定要贯彻执行统筹兼顾、全面安排的方针。","box":[[103,1154],[823,1157],[823,1190],[102,1187]]},{"text":"统筹兼顾，全面安排，这是我党历来的方针。这是一","box":[[105,1242],[841,1247],[840,1278],[104,1273]]},{"text":"个什么方针呢？就是调动一切积极力量，为了建设社会主","box":[[44,1302],[843,1307],[842,1338],[44,1332]]},{"text":"63-","box":[[764,1372],[816,1372],[816,1386],[764,1386]]}],"dimensions":{"height":1467,"width":964}}