{"ocr_results":[{"text":"(5)","box":[[733,58],[777,58],[777,89],[733,89]]},{"text":"it starting to change right before I left in 1978,although I was","box":[[207,156],[1269,158],[1269,185],[207,183]]},{"text":"in the research institute by then.  At that time the reputation and cred-","box":[[207,189],[1400,189],[1400,218],[207,218]]},{"text":"ibility of political activists began to decrease drastically，","box":[[209,221],[1241,224],[1241,251],[209,248]]},{"text":"Before","box":[[1237,226],[1334,226],[1334,247],[1237,247]]},{"text":"1977 class background was very important in determining who could be","box":[[207,254],[1321,255],[1321,285],[207,284]]},{"text":"anactivist.","box":[[213,291],[440,291],[440,312],[213,312]]},{"text":" Worker and peasant backgrounds made it relatively","box":[[426,287],[1245,288],[1245,318],[426,317]]},{"text":"easy;","box":[[1235,290],[1333,293],[1332,318],[1234,315]]},{"text":"cadres children had it really easy.","box":[[211,321],[800,324],[800,350],[211,347]]},{"text":"Almost all were young; its","box":[[811,322],[1236,323],[1236,351],[811,350]]},{"text":"Iaughable for an old person to act like an activist.(","box":[[208,353],[1099,354],[1099,383],[208,382]]},{"text":"Old workers would","box":[[1088,356],[1368,354],[1368,378],[1088,379]]},{"text":"help out a 1ot, but weren't activists or backbones. They didn't do","box":[[207,387],[1303,387],[1303,414],[207,414]]},{"text":"this for any advantage.","box":[[209,418],[609,423],[609,451],[209,446]]},{"text":"There is a rough dividing","box":[[615,419],[1033,421],[1033,448],[615,446]]},{"text":"glineat aboutage","box":[[1018,416],[1318,421],[1318,451],[1018,446]]},{"text":"40.","box":[[208,451],[271,453],[270,478],[207,475]]},{"text":"After that the demands for activism drop off.","box":[[290,455],[1022,455],[1022,479],[290,479]]},{"text":"Activists are less important now because Deng stresses real","box":[[305,484],[1270,484],[1270,516],[305,516]]},{"text":"ability.","box":[[210,518],[374,521],[373,545],[210,542]]},{"text":"Also there are basically no political movements, so how can","box":[[369,519],[1335,519],[1335,546],[369,546]]},{"text":"you show your political biaoxian?","box":[[207,552],[749,551],[749,578],[207,579]]},{"text":"Everyone can be good at politics","box":[[779,553],[1301,553],[1301,580],[779,580]]},{"text":"if they want, anyone can kiss ass and cultivate personal realtions (gao","box":[[207,583],[1367,582],[1367,613],[207,614]]},{"text":"guanxi）.","box":[[211,620],[369,618],[370,642],[211,645]]},{"text":"But now that politicalenvironment has changed,talking and","box":[[370,618],[1337,618],[1337,644],[370,644]]},{"text":"guanxi are less important and ability is more important.","box":[[207,649],[1125,648],[1125,678],[207,679]]},{"text":"Now less incentive exists for people to be activists, and many","box":[[304,681],[1320,682],[1320,712],[304,711]]},{"text":"people now want to just go home after work.(","box":[[207,718],[950,715],[950,742],[207,745]]},{"text":"Of course they still have","box":[[940,716],[1354,716],[1354,743],[940,743]]},{"text":"meetings and documents and small campaigns, but the scope for activists","box":[[205,750],[1369,748],[1369,778],[205,780]]},{"text":"has been restricted and the scope of real ability increased.A","box":[[205,782],[1229,780],[1229,807],[205,808]]},{"text":"Activists","box":[[1217,783],[1367,783],[1367,804],[1217,804]]},{"text":"are on the decline now because their functions are fewer,as is the","box":[[207,815],[1303,813],[1303,840],[207,842]]},{"text":"case in the propaganda department.(","box":[[210,849],[805,849],[805,876],[210,876]]},{"text":"Of course they will always be","box":[[791,847],[1270,846],[1270,874],[791,875]]},{"text":"needed, you can't do away with them entirely.","box":[[207,880],[944,881],[944,908],[207,907]]},{"text":"Peoplegenerallyacceptthe","box":[[975,882],[1417,880],[1417,907],[975,909]]},{"text":"promotionof peoplewhosimplydogoodwork.","box":[[207,914],[964,913],[964,939],[207,940]]},{"text":"But they still don't","box":[[959,913],[1288,912],[1288,938],[959,939]]},{"text":"like the activist who is seen as trying to be an official. You can","box":[[207,944],[1306,943],[1306,973],[207,974]]},{"text":"see it when people 1eave the plant to go home.(","box":[[208,982],[1001,982],[1001,1006],[208,1006]]},{"text":"Ordinaryworkerswalk","box":[[992,980],[1336,978],[1336,1003],[992,1005]]},{"text":"in groups and talk among","box":[[207,1012],[605,1014],[605,1041],[207,1039]]},{"text":"themselves.","box":[[614,1016],[832,1016],[832,1037],[614,1037]]},{"text":"Activists walk all by themselves.","box":[[829,1012],[1365,1012],[1365,1036],[829,1036]]},{"text":"At the bus stops,nobody talks to them.Of course activists aren't too","box":[[207,1047],[1368,1045],[1368,1071],[207,1073]]},{"text":"willing to talk and be friendly with ordinary people either, but the","box":[[206,1077],[1322,1075],[1322,1106],[206,1108]]},{"text":"feeling is mutual. But this is my personal opinion toward activists--","box":[[207,1108],[1351,1107],[1351,1141],[207,1142]]},{"text":"others might say they are really OK.","box":[[208,1143],[796,1142],[796,1172],[208,1173]]},{"text":"Ordinary activists:","box":[[306,1176],[652,1179],[652,1207],[306,1203]]},{"text":"the most important reward is promotion to","box":[[648,1178],[1322,1175],[1322,1201],[648,1205]]},{"text":"group leader or something else in the section or shop.","box":[[208,1211],[1120,1206],[1121,1236],[208,1240]]},{"text":"But there are also","box":[[1126,1209],[1417,1206],[1417,1230],[1126,1232]]},{"text":"psychological rewards that come from the status of being a leader and","box":[[208,1243],[1341,1237],[1341,1268],[208,1274]]},{"text":"'getting","box":[[215,1277],[345,1280],[344,1305],[215,1302]]},{"text":"g intothe Youth League' and \"getting intothe Party\"\".","box":[[331,1278],[1241,1272],[1241,1299],[331,1305]]},{"text":"The","box":[[1237,1274],[1287,1274],[1287,1297],[1237,1297]]},{"text":"material things are not always foremost in the minds of the activist.","box":[[205,1309],[1335,1305],[1335,1335],[205,1339]]},{"text":"There is glory in being an activist.","box":[[208,1341],[835,1340],[835,1370],[208,1371]]},{"text":"Butofcoursetheactivistis","box":[[829,1343],[1304,1339],[1304,1361],[829,1365]]},{"text":"always the first one to","box":[[212,1376],[591,1376],[591,1400],[212,1400]]},{"text":"0 get wage raises, and there are other rewards:","box":[[578,1376],[1337,1370],[1337,1397],[578,1403]]},{"text":"for example, its easier to get a girlfried if you are an activist","box":[[209,1410],[1273,1404],[1273,1431],[209,1437]]},{"text":"or leader, and the same goes for getting a wife.","box":[[208,1442],[1025,1439],[1025,1467],[208,1470]]},{"text":"It's alsoeasierfor","box":[[1028,1439],[1354,1437],[1354,1462],[1028,1464]]},{"text":"them to get housing (although this is less the case now).1","box":[[210,1475],[1181,1471],[1182,1498],[210,1502]]},{"text":"Before","box":[[1174,1470],[1274,1473],[1273,1497],[1173,1494]]},{"text":"1978 at 1east,it was unthinkable that ordinary people would be able","box":[[208,1508],[1321,1503],[1321,1530],[208,1535]]},{"text":"to out-compete an.lactivist for housing.","box":[[208,1541],[846,1540],[846,1568],[208,1569]]},{"text":"Shop Floor Activists","box":[[213,1600],[544,1600],[544,1624],[213,1624]]},{"text":"(10/11/83, 2 hrs.)","box":[[569,1600],[862,1600],[862,1624],[569,1624]]},{"text":"First of all,there's a difference between the activities of","box":[[307,1631],[1293,1628],[1293,1655],[307,1658]]},{"text":"activists who are group leaders and shift leaders, and those who","box":[[209,1664],[1259,1659],[1259,1689],[209,1694]]},{"text":"are not. The heads of groups are always activists. T","box":[[209,1697],[1091,1695],[1091,1725],[209,1727]]},{"text":"Therewerefour","box":[[1077,1698],[1326,1698],[1326,1721],[1077,1721]]},{"text":"in my section.","box":[[211,1733],[470,1733],[470,1760],[211,1760]]},{"text":"The main reward is that they eventually wii1 get promoted","box":[[471,1732],[1408,1732],[1408,1756],[471,1756]]},{"text":"or get wage raises before everyone else,","box":[[209,1765],[874,1762],[874,1791],[209,1794]]},{"text":"Buttherealincentive","box":[[899,1764],[1267,1764],[1267,1787],[899,1787]]},{"text":"is","box":[[1256,1764],[1307,1764],[1307,1785],[1256,1785]]},{"text":"that this is the first step on the road to becoming an official.","box":[[209,1795],[1261,1794],[1261,1824],[209,1825]]},{"text":"If you aren't already a youth league member by this","box":[[210,1831],[1053,1828],[1053,1855],[210,1858]]},{"text":" time,you join.","box":[[1042,1831],[1307,1828],[1307,1856],[1042,1859]]},{"text":"After you're a group leader its easier to get into the Party.B","box":[[209,1863],[1254,1861],[1254,1891],[209,1893]]},{"text":"Entering","box":[[1240,1861],[1378,1865],[1377,1893],[1239,1888]]},{"text":"the Party and the youth league is itself a step towards becoming an","box":[[209,1896],[1312,1895],[1312,1924],[209,1925]]},{"text":"official in many people's minds anyway, because it leads to later","box":[[209,1929],[1278,1928],[1278,1956],[209,1957]]}],"dimensions":{"height":2129,"width":1566}}